dingonyms.py
dingonyms-0.8.data/data/man/man1/dingonyms.1
dingonyms-0.8.dist-info/METADATA
dingonyms-0.8.dist-info/WHEEL
dingonyms-0.8.dist-info/entry_points.txt
dingonyms-0.8.dist-info/top_level.txt
dingonyms-0.8.dist-info/RECORD
