Metadata-Version: 2.1
Name: dingonyms
Version: 0.8
Summary: fetch synonyms from various web services
Home-page: https://fossil.include-once.org/pagetranslate/wiki/dingonyms
License: PD
Keywords: glossary,synonyms,antonyms
Classifier: License :: Public Domain
Classifier: Topic :: Communications :: Email :: Filters
Classifier: Topic :: Internet :: WWW/HTTP :: Indexing/Search
Classifier: Topic :: Text Processing :: Filters
Requires-Python: >= 3.6
Requires-Dist: requests (>=2.4)
